{
  "id": "00000000-0000-0000-0000-000000000000",
  "prevId": "",
  "version": "7",
  "dialect": "postgresql",
  "tables": {
    "public.transaction_records": {
      "name": "transaction_records",
      "schema": "",
      "columns": {
        "id": {
          "name": "id",
          "type": "uuid",
          "primaryKey": true,
          "notNull": true,
          "default": "gen_random_uuid()"
        },
        "created_at": {
          "name": "created_at",
          "type": "timestamp with time zone",
          "primaryKey": false,
          "notNull": true,
          "default": "now()"
        },
        "updated_at": {
          "name": "updated_at",
          "type": "timestamp with time zone",
          "primaryKey": false,
          "notNull": true,
          "default": "now()"
        },
        "seller_wallet": {
          "name": "seller_wallet",
          "type": "varchar",
          "primaryKey": false,
          "notNull": true
        },
        "buyer_wallet": {
          "name": "buyer_wallet",
          "type": "varchar",
          "primaryKey": false,
          "notNull": false
        },
        "description": {
          "name": "description",
          "type": "text",
          "primaryKey": false,
          "notNull": false
        },
        "title": {
          "name": "title",
          "type": "text",
          "primaryKey": false,
          "notNull": false
        },
        "seller_nft": {
          "name": "seller_nft",
          "type": "text",
          "primaryKey": false,
          "notNull": false
        },
        "buyer_nft": {
          "name": "buyer_nft",
          "type": "text",
          "primaryKey": false,
          "notNull": false
        }
      },
      "indexes": {},
      "foreignKeys": {},
      "compositePrimaryKeys": {},
      "uniqueConstraints": {},
      "checkConstraints": {},
      "policies": {},
      "isRLSEnabled": true
    }
  },
  "enums": {},
  "schemas": {},
  "sequences": {},
  "roles": {},
  "policies": {},
  "views": {},
  "_meta": {
    "schemas": {},
    "tables": {},
    "columns": {}
  },
  "internal": {
    "tables": {}
  }
}